pyquire/__init__.py
pyquire/api.py
pyquire/credentials.py
pyquire/models/__init__.py
pyquire/models/attachment.py
pyquire/models/column.py
pyquire/models/common.py
pyquire/models/entity.py
pyquire/models/identity.py
pyquire/models/identity_x.py
pyquire/models/named_entity.py
pyquire/models/named_icon_entity.py
pyquire/models/recurring.py
pyquire/models/referrer.py
pyquire/models/stamped_entity.py
pyquire/models/tagging_entity.py
pyquire/models/board/__init__.py
pyquire/models/board/add_column_body.py
pyquire/models/board/board.py
pyquire/models/board/create_board_body.py
pyquire/models/board/create_column_body.py
pyquire/models/board/update_board_body.py
pyquire/models/board/update_column_body.py
pyquire/models/comment/__init__.py
pyquire/models/comment/comment.py
pyquire/models/comment/create_comment_body.py
pyquire/models/comment/update_comment_body.py
pyquire/models/externalteam/__init__.py
pyquire/models/externalteam/partner.py
pyquire/models/organization/__init__.py
pyquire/models/organization/organization.py
pyquire/models/project/__init__.py
pyquire/models/project/project.py
pyquire/models/project/update_project_body.py
pyquire/models/tag/__init__.py
pyquire/models/tag/create_tag_body.py
pyquire/models/tag/tag.py
pyquire/models/tag/update_tag_body.py
pyquire/models/task/__init__.py
pyquire/models/task/create_task_body.py
pyquire/models/task/search_task_body.py
pyquire/models/task/simple_task.py
pyquire/models/task/task.py
pyquire/models/task/update_task_body.py
pyquire/models/user/__init__.py
pyquire/models/user/user.py
pyquire/resources/__init__.py
pyquire/resources/board_resource.py
pyquire/resources/comment_resource.py
pyquire/resources/organization_resource.py
pyquire/resources/partner_resource.py
pyquire/resources/project_resource.py
pyquire/resources/tag_resource.py
pyquire/resources/task_resource.py
pyquire/resources/user_resource.py
pyquire-1.0.4.dist-info/LICENSE
pyquire-1.0.4.dist-info/METADATA
pyquire-1.0.4.dist-info/WHEEL
pyquire-1.0.4.dist-info/top_level.txt
pyquire-1.0.4.dist-info/RECORD
