Metadata-Version: 2.1
Name: pyquire
Version: 1.0.4
Summary: Object Oriented API for Quire
Home-page: https://gitlab.com/MVDraurus/pyquire
Author: Vadym Matus
Author-email: vadym.matus@gmail.com
License: UNKNOWN
Platform: UNKNOWN
Classifier: Programming Language :: Python :: 3
Classifier: Operating System :: OS Independent
Requires-Python: >=3.8
Requires-Dist: Flask (<1.2.0,>=1.1.2)
Requires-Dist: requests (<2.24.0,>=2.23.0)
Requires-Dist: attrs (<19.4,>=19.3.0)
Requires-Dist: singleton (<0.2.0,>=0.1.0)
